git_pyinit/__about__.py
git_pyinit/__init__.py
git_pyinit/cli.py
git_pyinit/config.toml
git_pyinit/toml_reader.py
git_pyinit/utils.py
git_pyinit/exceptions/common.py
git_pyinit-1.3.4.dist-info/METADATA
git_pyinit-1.3.4.dist-info/WHEEL
git_pyinit-1.3.4.dist-info/entry_points.txt
git_pyinit-1.3.4.dist-info/licenses/LICENSE.txt
git_pyinit-1.3.4.dist-info/RECORD
