Metadata-Version: 2.3
Name: git-pyinit
Version: 1.3.4
Project-URL: Documentation, https://github.com/Lumesque/git-pyinit#readme
Project-URL: Issues, https://github.com/Lumesque/git-pyinit/issues
Project-URL: Source, https://github.com/Lumesque/git-pyinit
Author-email: Joshua Luckie <luckiejoshu@gmail.com>
License-Expression: MIT
License-File: LICENSE.txt
Classifier: Development Status :: 4 - Beta
Classifier: Programming Language :: Python
Classifier: Programming Language :: Python :: 3.8
Classifier: Programming Language :: Python :: 3.9
Classifier: Programming Language :: Python :: 3.10
Classifier: Programming Language :: Python :: 3.11
Classifier: Programming Language :: Python :: 3.12
Classifier: Programming Language :: Python :: Implementation :: CPython
Classifier: Programming Language :: Python :: Implementation :: PyPy
Requires-Python: >=3.8
Requires-Dist: hatch
Requires-Dist: toml
